chinese_comment_remover/__init__.py
chinese_comment_remover/remove.py
scripts/__init__.py
scripts/remove_comment.py
chinese_comment_remover-0.0.0.1.dist-info/METADATA
chinese_comment_remover-0.0.0.1.dist-info/WHEEL
chinese_comment_remover-0.0.0.1.dist-info/entry_points.txt
chinese_comment_remover-0.0.0.1.dist-info/top_level.txt
chinese_comment_remover-0.0.0.1.dist-info/RECORD
