Metadata-Version: 2.1
Name: chinese-comment-remover
Version: 0.0.0.1
Summary: A tool to remove comments [with Chinese] characters from Python files.
Author: steveflyer
Author-email: steveflyer7@gmail.com
Requires-Dist: black
